regmonkey_style/__init__.py
regmonkey_style/common/setup_custom_font.py
regmonkey_style/common/utils.py
regmonkey_style/config.py
regmonkey_style/configs/config.yaml
regmonkey_style/fonts/IPAexGothic/IPA_Font_License_Agreement_v1.0.txt
regmonkey_style/fonts/IPAexGothic/Readme_ipaexg00401.txt
regmonkey_style/fonts/IPAexGothic/ipaexg.ttf
regmonkey_style/fonts/MPLUS1p/MPLUS1p-Regular.ttf
regmonkey_style/fonts/MPLUS1p/OFL.txt
regmonkey_style/matplotlib_custom/templates.py
regmonkey_style/plotly_custom/templates.py
regmonkey_style/stylewizard.py
regmonkey_style-2.0.0.dist-info/LICENSE
regmonkey_style-2.0.0.dist-info/METADATA
regmonkey_style-2.0.0.dist-info/WHEEL
regmonkey_style-2.0.0.dist-info/RECORD
