Metadata-Version: 2.3
Name: regmonkey_style
Version: 2.0.0
Summary: plotly and matplotlib style for statistics-for-regression-monkey
License: MIT
Author: RyoNak
Author-email: nakagamiryo0901@gmail.com
Requires-Python: >=3.11,<4.0
Classifier: License :: OSI Approved :: MIT License
Classifier: Programming Language :: Python :: 3
Classifier: Programming Language :: Python :: 3.11
Classifier: Programming Language :: Python :: 3.12
Classifier: Programming Language :: Python :: 3.13
Requires-Dist: kaleido (>=1.0.0,<2.0.0)
Requires-Dist: matplotlib (>=3.9.2,<4.0.0)
Requires-Dist: plotly (>=6.2.0,<7.0.0)
Requires-Dist: pydantic (>=2.9.2,<3.0.0)
Requires-Dist: pyyaml (>=6.0.2,<7.0.0)
Requires-Dist: seaborn (>=0.13.2,<0.14.0)
Project-URL: Homepage, https://github.com/RyoNakagami
Project-URL: Repository, https://github.com/RyoNakagami/regmonkey-style
